{
  "full_name": "Bethany Edwards",
  "email": "bethany.edwards@protonmail.com",
  "location": "Smithmouth, Germany",
  "years_of_experience": 11.3,
  "seniority_level": "lead",
  "primary_domain": "Design (UI/UX)",
  "has_github": true,
  "has_linkedin": true,
  "contact_info": {
    "full_name": "Bethany Edwards",
    "email": "bethany.edwards@protonmail.com",
    "phone": "(590)340-9836x6552",
    "location": "Smithmouth, Germany",
    "linkedin_url": "https://linkedin.com/in/bethany-edwards",
    "github_url": "https://github.com/bethanyedwards",
    "portfolio_url": null
  },
  "summary": "Senior technical leader specializing in design (ui/ux) with expertise in Python, JavaScript, HTML. Proven success in technical vision, team development, and stakeholder management.",
  "work_experience": [
    {
      "company": "ResumeAI",
      "organization": "ResumeAI",
      "job_title": "Visual Designer",
      "title": "Visual Designer",
      "start_date": "2022-05",
      "end_date": "Present",
      "duration": "2022-05 – Present",
      "duration_months": 46,
      "description": "Conducted usability testing using InVision, identifying 10000+ UX issues\nBuilt interactive prototypes using Principle, reducing development cycles by 49%\nDesigned user interfaces using Adobe XD, improving usability by 42%",
      "technologies": [
        "Principle",
        "Adobe XD",
        "InVision",
        "JavaScript",
        "User Research"
      ],
      "is_remote": false,
      "employment_type": "full-time"
    },
    {
      "company": "Palantir",
      "organization": "Palantir",
      "job_title": "Visual Designer",
      "title": "Visual Designer",
      "start_date": "2018-10",
      "end_date": "2022-03",
      "duration": "2018-10 – 2022-03",
      "duration_months": 41,
      "description": "Created brand identity using Zeplin, applied across 100+ touchpoints\nConducted user research using Usability Testing, gathering insights from 100+ users\nConducted usability testing using Usability Testing, identifying 100+ UX issues\nBuilt design collaboration workflow using Maze, reducing review time by 67%",
      "technologies": [
        "Maze",
        "Accessibility (WCAG)",
        "Usability Testing",
        "Zeplin",
        "Hotjar"
      ],
      "is_remote": false,
      "employment_type": "part-time"
    },
    {
      "company": "Twilio",
      "organization": "Twilio",
      "job_title": "UX Designer",
      "title": "UX Designer",
      "start_date": "2014-03",
      "end_date": "2018-04",
      "duration": "2014-03 – 2018-04",
      "duration_months": 49,
      "description": "Created information architecture using Framer, improving navigation by 34%\nDesigned user interfaces using Design Thinking, improving usability by 44%",
      "technologies": [
        "Python",
        "Framer",
        "Zeplin",
        "Design Thinking"
      ],
      "is_remote": false,
      "employment_type": "full-time"
    }
  ],
  "education": [
    {
      "institution": "Columbia University",
      "university": "Columbia University",
      "degree": "B.Sc.",
      "field_of_study": "Mathematics",
      "graduation_date": "2014",
      "gpa": "3.73",
      "activities": null
    }
  ],
  "skills": [
    {
      "skill_name": "Python",
      "category": "programming_language",
      "source": "explicit"
    },
    {
      "skill_name": "JavaScript",
      "category": "programming_language",
      "source": "explicit"
    },
    {
      "skill_name": "HTML",
      "category": "programming_language",
      "source": "explicit"
    },
    {
      "skill_name": "CSS",
      "category": "programming_language",
      "source": "explicit"
    },
    {
      "skill_name": "Framer",
      "category": "framework",
      "source": "explicit"
    },
    {
      "skill_name": "InVision",
      "category": "framework",
      "source": "explicit"
    },
    {
      "skill_name": "Figma",
      "category": "framework",
      "source": "explicit"
    },
    {
      "skill_name": "Adobe XD",
      "category": "framework",
      "source": "explicit"
    },
    {
      "skill_name": "Principle",
      "category": "framework",
      "source": "explicit"
    },
    {
      "skill_name": "Maze",
      "category": "tool",
      "source": "explicit"
    },
    {
      "skill_name": "Miro",
      "category": "tool",
      "source": "explicit"
    },
    {
      "skill_name": "Adobe Creative Suite",
      "category": "tool",
      "source": "explicit"
    },
    {
      "skill_name": "Zeplin",
      "category": "tool",
      "source": "explicit"
    },
    {
      "skill_name": "Firebase",
      "category": "database",
      "source": "explicit"
    },
    {
      "skill_name": "Vercel",
      "category": "cloud",
      "source": "explicit"
    },
    {
      "skill_name": "Cloudflare",
      "category": "cloud",
      "source": "explicit"
    },
    {
      "skill_name": "Netlify",
      "category": "cloud",
      "source": "explicit"
    },
    {
      "skill_name": "Design Thinking",
      "category": "methodology",
      "source": "explicit"
    },
    {
      "skill_name": "Usability Testing",
      "category": "methodology",
      "source": "explicit"
    },
    {
      "skill_name": "Accessibility (WCAG)",
      "category": "methodology",
      "source": "explicit"
    },
    {
      "skill_name": "Prototyping",
      "category": "methodology",
      "source": "explicit"
    },
    {
      "skill_name": "User Research",
      "category": "other",
      "source": "inferred"
    }
  ],
  "projects": [
    {
      "name": "Health Check Service",
      "description": "Created Style Guide leveraging CSS for core functionality and Framer for optimization",
      "technologies": [
        "Adobe XD",
        "CSS",
        "Framer"
      ],
      "url": "https://github.com/bethanyedwards/health-check-service",
      "date": "2021"
    },
    {
      "name": "Task Scheduler",
      "description": "Implemented Brand Identity using Figma, achieving 99.9% uptime and handling 50k+ requests daily",
      "technologies": [
        "Figma",
        "HTML",
        "Adobe XD"
      ],
      "url": null,
      "date": "2025"
    }
  ],
  "certifications": [],
  "misc_data": [
    {
      "label": "personal_statement",
      "raw_text": "Passionate about AI ethics and building technology that makes a difference.",
      "structured": null
    },
    {
      "label": "publication",
      "raw_text": "\"Certain wall student matter lay own certainly program\" — NeurIPS 2020",
      "structured": null
    },
    {
      "label": "volunteering",
      "raw_text": "Volunteer coding instructor at Johnson, Flores and Shaw Youth Program, 2024-Present",
      "structured": null
    }
  ],
  "skills_flat": [
    "Python",
    "JavaScript",
    "HTML",
    "CSS",
    "Framer",
    "InVision",
    "Figma",
    "Adobe XD",
    "Principle",
    "Maze",
    "Miro",
    "Adobe Creative Suite",
    "Zeplin",
    "Firebase",
    "Vercel",
    "Cloudflare",
    "Netlify",
    "Design Thinking",
    "Usability Testing",
    "Accessibility (WCAG)",
    "Prototyping"
  ],
  "companies": [
    "ResumeAI",
    "Palantir",
    "Twilio"
  ],
  "job_titles": [
    "Visual Designer",
    "Visual Designer",
    "UX Designer"
  ],
  "universities": [
    "Columbia University"
  ],
  "degrees": [
    "B.Sc."
  ],
  "parsing_metadata": {
    "cv_id": 389,
    "tier": "T1",
    "domain": "design",
    "generated_at": "2026-03-18T12:40:34.374369",
    "content_source": "template",
    "template": "T1_executive"
  }
}